my_pypi_test_pkg_syjiang/__init__.py
my_pypi_test_pkg_syjiang/greeter.py
my_pypi_test_pkg_syjiang-0.0.1.dist-info/METADATA
my_pypi_test_pkg_syjiang-0.0.1.dist-info/WHEEL
my_pypi_test_pkg_syjiang-0.0.1.dist-info/RECORD
