Metadata-Version: 2.4
Name: my_pypi_test_pkg_syjiang
Version: 0.0.1
Summary: A small example package for PyPI testing
Project-URL: Homepage, https://github.com/jiangsanyin/my_pypi_test_pkg
Project-URL: Bug Tracker, https://github.com/jiangsanyin/my_pypi_test_pkg/issues
Author-email: syjiang <1327212357@qq.com>
Classifier: License :: OSI Approved :: MIT License
Classifier: Operating System :: OS Independent
Classifier: Programming Language :: Python :: 3
Requires-Python: >=3.7
